renovosolutions_recommended_cloudwatch_alarms/__init__.py
renovosolutions_recommended_cloudwatch_alarms/py.typed
renovosolutions_recommended_cloudwatch_alarms/_jsii/__init__.py
renovosolutions_recommended_cloudwatch_alarms/_jsii/cdk-library-cloudwatch-alarms@0.0.14.jsii.tgz
renovosolutions_aws_cdk_cloudwatch_alarms-0.0.14.dist-info/LICENSE
renovosolutions_aws_cdk_cloudwatch_alarms-0.0.14.dist-info/METADATA
renovosolutions_aws_cdk_cloudwatch_alarms-0.0.14.dist-info/WHEEL
renovosolutions_aws_cdk_cloudwatch_alarms-0.0.14.dist-info/top_level.txt
renovosolutions_aws_cdk_cloudwatch_alarms-0.0.14.dist-info/RECORD
